fsaccone/__init__.py
fsaccone/app/__init__.py
fsaccone/app/build.py
fsaccone/app/cli/__init__.py
fsaccone/app/cli/confirm.py
fsaccone/app/cli/help.py
fsaccone/app/cli/unknown.py
fsaccone/app/start.py
fsaccone/app/utils/__init__.py
fsaccone/app/utils/fetch.py
fsaccone/app/utils/logger.py
fsaccone/app/utils/templates.py
fsaccone/args.py
fsaccone/main.py
fsaccone-1.0.2.dist-info/entry_points.txt
fsaccone-1.0.2.dist-info/LICENSE.txt
fsaccone-1.0.2.dist-info/METADATA
fsaccone-1.0.2.dist-info/WHEEL
fsaccone-1.0.2.dist-info/RECORD
